terraguard/__init__.py
terraguard/_version.py
terraguard/terraguard.py
terraguard/validators.py
terraguard/resources/__init__.py
terraguard/resources/aws/__init__.py
terraguard/resources/aws/aws_ec2.py
terraguard/resources/aws/aws_ecr.py
terraguard/resources/aws/aws_elb.py
terraguard/resources/aws/aws_lb.py
terraguard/resources/aws/aws_sqs.py
terraguard/resources/aws/aws_vpc.py
terraguard/resources/aws/resource.py
terraguard/resources/aws/taggable_resources.py
terraguard/validators/__init__.py
terraguard/validators/must_contain.py
terraguard/validators/must_equal.py
terraguard/validators/must_not_contain.py
terraguard-0.0.2.dist-info/LICENSE
terraguard-0.0.2.dist-info/METADATA
terraguard-0.0.2.dist-info/WHEEL
terraguard-0.0.2.dist-info/entry_points.txt
terraguard-0.0.2.dist-info/top_level.txt
terraguard-0.0.2.dist-info/RECORD
